Workbook

Sheet Revenue
A1: F | B1: Project | C1: Budget (including GST) | D1: Date | E1: Advance/Payment | F1: Amount | G1: TDS amount | H1: Balance | I1: Column 1
A2: 1 | B2: Think9(Broadway) | C2: 59000 | D2: 45777 | E2: Full Payment | F2: 54000 | G2: =C2-F2 -> 5000 | H2: 0
G3: =C3-F3 -> 0
A4: 2 | B4: Dabbahwala LLc - April LYF | D4: 45748 | E4: Full Payment | F4: 400000 | G4: 0 | H4: 0
A5: 3 | B5: Finone(Disruptive Media) -LFY | D5: 45749 | E5: Full Payment | F5: 348000 | G5: 6000 | H5: 0
A6: 4 | B6: Think9(Broadway) - Balance Payment of last FY project | D6: 45754 | E6: Full payment WO GST | F6: 100000 | G6: 4600 | H6: 0
D7: 45756 | E7: pending gst payment | F7: 55200 | H7: 0
A8: 5 | B8: Bambinos -LFY | D8: 45754 | E8: Balance 35% (2nd Installment) | F8: 264600
D9: 45772 | E9: Balance 30% (Balance Payment) | F9: 226800 | G9: 70000
A10: 6 | B10: Hala Mobility - March - Retainer Fees - (March) Last FY | D10: 45762 | E10: march month retainer payment | F10: 147000 | G10: 30000 | H10: 0
A11: 7 | B11: Pranita Bajoria - Apoorv Guest Session | C11: 15000 | D11: 45750 | E11: Full Payment | F11: 15000 | G11: 0 | H11: 0
A12: 8 | B12: Rapture Innovation - Sonic Lamb | D12: 45755 | E12: 50% Advance Payment | F12: 290000
D13: 45790 | E13: 50% balance Payment | F13: 290000 | G13: 10000
A14: 9 | B14: Zomato Packathon Event | C14: 684400 | D14: 45811 | E14: Full payment | F14: 672800 | G14: 11600 | H14: 0
A15: 10 | B15: Nxtwave(3 vdos) | C15: 283200 | D15: 45764 | E15: Full Payment | F15: 259200 | G15: 24000 | H15: 0
A16: 11 | B16: ITC Sunrise(Social) | C16: 177000 | D16: 45852 | E16: Full Payment | F16: 162000 | G16: =C16-F16 -> 15000 | H16: 0
A17: 12 | B17: Thub Corporate Short Vdo(LYF) | D17: 45785 | E17: Balance payment | F17: 40500 | G17: 3750
A18: 13 | B18: Dabbahwala LLC - May Retainer Fees(LFY) | D18: 45791 | E18: Advance payment | F18: 300000
D19: 45797 | E19: Balance payment | F19: 150000
A20: 14 | B20: Abhibus Balance(LFY project) | D20: 45772 | E20: Balance | F20: 161640
D21: 45777 | E21: Gst Amount | F21: 57240 | G21: 6360
A22: 15 | B22: Hala Mobility - Retainer Fees - April(lyf) | D22: 45787 | E22: Full payment - May | F22: 162000 | G22: 15000 | H22: 0
A23: 16 | B23: Sattva IP's | C23: 2478000 | D23: 45810 | E23: 60% Advance payment | F23: 1392000 | G23: =C23-F23-F24 -> 42000 | H23: 0
D24: 45839 | E24: 40% advance payment | F24: 1044000
A26: 17 | B26: TCS(Ayanz food lab) - Retainer - May | C26: 531000 | D26: 45782 | E26: Advance | F26: =50000+150000 -> 200000 | H26: =C26-F26-F27-F28-F29 -> 31000
D27: 45783 | E27: Advance | F27: 50000
D28: 45794 | E28: Advance | F28: 150000
D29: 45810 | E29: balance | F29: 100000
A30: 18 | B30: TCS(Ayanz food lab) - Retainer - June | C30: 385500 | D30: 45850 | E30: full payment without gst | F30: 325000 | H30: =C30-F30 -> 60500
B32: TCS - Retainer - Jan 26
B33: TCS - Retainer - Feb 26
B34: TCS - Retainer - March 26
A35: 19 | B35: Zomato Voice Over - dubs | C35: 100300 | D35: 45821 | E35: Full Payment | F35: 98600 | G35: 1700 | H35: 0
A36: 20 | B36: Nxtwave Lab Innovation Vdo | C36: 330400 | D36: 45793 | E36: Full Payment | F36: 324800 | G36: 5600 | H36: 0
A37: 21 | B37: Select(Celeket Gadgets) | C37: 1700000 | D37: 45800 | E37: 30% advance Payment | F37: 435000 | H37: 0
D38: 45826 | E38: Advance | F38: 700000
D39: 45847 | E39: Balance Payment | F39: 565000
A41: 22 | B41: Hala Mobility Monthly Retainer - May | C41: 177000 | D41: 45815 | E41: Full Payment | F41: 162000 | G41: 15000 | H41: 0
A43: 23 | B43: Zomato Dub - Monika | C43: 70210
A45: 24 | B45: Dabbahwala LLC - June Retainer Fees(LFY) | D45: 45814 | E45: Full Payment | F45: 450000 | G45: 0
A46: 25 | B46: Nxtwave green Screen Shoot | C46: 29500 | D46: 45854 | E46: Full Payment | F46: 29000 | G46: 500 | H46: 0
A47: 26 | B47: Jumpp - Finfutech | C47: 2932300 | D47: 45828 | E47: 50% Advance | F47: 1395900 | G47: =129250+64625+54625 -> 248500 | H47: =C47-F47-F48-G47-F49 -> 0
D48: 45923 | E48: 25% balance | F48: 697950
D49: 46063 | E49: 25% Balance | F49: 589950
A51: 27 | B51: Jumpp Social Retainer - Finvasia | C51: 309750 | D51: 45834 | E51: 100% Payment | F51: 283500 | G51: 26250 | H51: =C51-F51-G51 -> 0
A54: 28 | B54: Zomato ITR Social | C54: 324500 | D54: 45880 | E54: Full Payment | F54: 319000 | G54: 5500 | H54: =C54-F54-G54 -> 0
A55: 29 | B55: Dabur India | C55: 572300 | D55: 45831 | E55: Dabur Kill Fees | F55: 562600 | G55: =C55-F55 -> 9700 | H55: 0
A56: 30 | B56: Medanta Hospitals - Global health | C56: =800000+144000 -> 944000 | D56: 45839 | E56: Full Payment | F56: 864000 | G56: =C56-F56 -> 80000 | H56: 0
A58: 31 | B58: Zomato Reactivate | C58: 767000 | D58: 45895 | E58: Full Payment | F58: 754000 | G58: =C58-F58 -> 13000 | H58: 0
A59: 32 | B59: Hala Mobility - June | C59: 295000 | D59: 45849 | E59: Full Payment | F59: 270000 | G59: 25000 | H59: 0
A60: 33 | B60: Karya & Gravity Zip Retainer - July | C60: 253700 | D60: 45839 | E60: Gravityzip Full Payment | F60: 135000 | G60: 12500
D61: 45841 | E61: Karya Full Payment | F61: 97200 | G61: 9000
B62: Karya & Gravity Zip Retainer - August | C62: 253700 | D62: 45876 | E62: Gravityzip Full Payment | F62: 135000 | G62: 12500
D63: 45876 | E63: Karya Full Payment | F63: 97200 | G63: 9000
B64: Karya & Dividant Retainer - September | C64: 253700 | D64: 45905 | E64: Karya Full Payment | F64: 104400 | G64: 1800
D65: 45909 | E65: Gzip partial Payment | F65: 100000
D66: 45923 | E66: Gzip Balance Payment | F66: 35000 | G66: 12500
B67: Karya & Gravity Zip Retainer - October | C67: 253700 | D67: 45937 | E67: Gravityzip Full Payment | F67: 135000 | G67: 12500
D68: 45937 | E68: Karya Full Payment | F68: 97200 | G68: 9000
B69: Karya & Gravity Zip Retainer - November | C69: 253700 | D69: 45966 | E69: Gravityzip Full Payment | F69: 135000 | G69: 12500
D70: 45966 | E70: Karya Full Payment | F70: 97200 | G70: 9000
B71: Karya & Gravity Zip Retainer - December | C71: 253700 | D71: 45993 | E71: Gravityzip Full Payment | F71: 145000 | G71: 2500
D72: 45993 | E72: Karya Full Payment | F72: 104400 | G72: 1800
B73: Karya & Gravity Zip Retainer - January | C73: 253700 | D73: 46030 | E73: Gravityzip Full Payment | F73: 104400 | G73: 1800
D74: 46042 | E74: Gravityzip Full Payment | F74: 145000 | G74: 2500
B75: Karya & Gravity Zip Retainer - February | C75: 147500 | D75: 46064 | E75: Karya Full Payment | F75: 145000 | G75: 2500
B76: Karya & Gravity Zip Retainer - March | C76: 147500 | D76: 46087 | E76: Karya Full Payment | F76: 145100 | G76: 2500
B77: Karya & Gravity Zip Retainer - April | C77: 147500
B78: Karya & Gravity Zip Retainer - May | C78: 147500
B79: Karya & Gravity Zip Retainer - June | C79: 147500
A81: 34 | B81: Rapture Innovation - Sonic Lamb Campaign | C81: 590000 | D81: 45847 | E81: 50% Advance Payment | F81: 290000 | G81: =C81-F81-F82 -> 10000
D82: 45975 | E82: 50% Balance Payment | F82: 290000
A84: 35 | B84: IIMR | D84: 45815 | E84: IIMR balance 50% | F84: 241525 | G84: 8475
A86: 36 | B86: ITC - 2 Months | C86: 354000 | D86: 45993 | E86: Full Payment | F86: 348000 | G86: 6000
A87: 37 | B87: Nxtwave | C87: 637200 | D87: 45855 | E87: Full Payment | F87: 580000 | G87: 10000 | H87: =C87-F87-F88-G87-G88 -> 0
D88: 45887 | E88: extra 40k for actors | F88: 46400 | G88: 800
A90: 38 | B90: Tirumala Jewellers | C90: 218300 | D90: 45848 | E90: 1st Month Full Payment | F90: 214600 | G90: =C90-F90 -> 3700 | H90: =C90-F90-G90 -> 0
A91: 39 | B91: Shakti Hormann | C91: 367500 | D91: 45868 | E91: Advance | F91: 367500
A95: 40 | B95: Snapdeal - WLDD | C95: 531000 | D95: 45856 | E95: 50% advance | F95: 220500 | G95: 9000 | H95: =C95-F95-F96-G96-G95 -> 81000
D96: 45926 | E96: 50% balance | F96: 220500
A98: 41 | B98: Nxtwave Contract - july | C98: 442500 | D98: 45890 | E98: full payment | F98: 435000 | G98: =C98-F98 -> 7500 | H98: =C98-F98-G98 -> 0
A100: 42 | B100: Hala July | C100: 295000 | D100: 45877 | E100: full payment | F100: 270000 | G100: =C100-F100 -> 25000 | H100: 0
B101: Hala August | C101: 295000 | D101: 45910 | E101: full payment | F101: 270000 | G101: 25000 | H101: 0
B102: Hala September | C102: 295000 | D102: 45940 | E102: full payment | F102: 270000 | G102: 25000 | H102: 0
B103: Hala October | C103: 295000 | D103: 45981 | E103: full payment | F103: 270000 | G103: 25000 | H103: 0
B104: Hala November | C104: 295000 | D104: 46013 | E104: full payment | F104: 270000 | G104: 25000 | H104: 0
A106: 43 | B106: Medanta - Global Health | C106: 5900000 | D106: 45888 | E106: 30% advance payment - Banno | F106: 1620000 | G106: 150000 | H106: =C106-F106-F107-F108-G106-G107-G108 -> 1888000
D107: 45904 | E107: 20% advance - Banno | F107: 1080000 | G107: 100000
D108: 45985 | E108: 20% Balance | F108: 972000 | G108: 90000
A110: 44 | B110: Zomato Earnpro | C110: 531000 | D110: 45952 | E110: Full payment | F110: 522000 | G110: =C110-F110 -> 9000 | H110: 0
A111: 45 | B111: Zomato - Dubs | C111: 277890 | D111: 46013 | E111: Full payment | F111: 273180 | G111: =C111-F111 -> 4710 | H111: 0
A113: 46 | B113: T-Bridge | C113: 94400 | D113: 45897 | E113: Full Payment | F113: 86400 | G113: 8000 | H113: 0
A114: 47 | B114: Zomato Sustainability EV Bazar | C114: 684400 | D114: 45918 | E114: Full Payment | F114: 672800 | G114: =C114-F114 -> 11600 | H114: 0
A116: 48 | B116: Dista | C116: 826000 | D116: 45904 | E116: 50% advance | F116: 373410 | G116: 0
D117: 45968 | E117: 50% balance | F117: 375863 | G117: 0
A119: 49 | B119: Paytm Bhaidooj | C119: 177000 | D119: 45971 | E119: Full Payment | F119: 174000 | G119: 3000
A121: 50 | B121: Paytm - Sept | C121: 501500 | D121: 45960 | E121: Full payment | F121: 459000 | G121: =C121-F121 -> 42500
B123: Paytm - Oct | C123: 501500 | D123: 45989 | E123: Full payment | F123: 459000 | G123: =C123-F123 -> 42500
B124: Paytm - Nov | C124: 501500 | D124: 46022 | E124: Full Payment | F124: 459000 | G124: =C124-F124 -> 42500
B125: Paytm - Dec | C125: 501500 | D125: 46059 | E125: Full Payment | F125: 459000 | G125: =C125-F125 -> 42500
...

Sheet Expenses
A1: S No. | B1: Type Of Expenses | C1: Project/operational | D1: Date | E1: Amount | F1: TDS | G1: Total Amount | H1: Column 1 | I1: Column 2 | J1: Column 3 | K1: Column 4
A2: 1 | B2: Mithil Sound | C2: Sattva Sound Design | D2: 45749 | E2: 30000 | F2: 0 | G2: 30000
A3: 2 | B3: Peter Makeup | C3: Abhibus Makeup | D3: 45749 | E3: 6500 | F3: 0 | G3: 6500
A4: 3 | B4: Sound Space | C4: TDP podcast Sync | D4: 45749 | E4: 2500 | F4: 0 | G4: 2500
A5: 4 | B5: Om Travels | C5: IP Shoot - Hyd food travel | D5: 45749 | E5: 4615 | F5: 0 | G5: 4615
A6: 5 | B6: MMT | D6: 45751 | E6: 40000 | F6: 0 | G6: =E6+F6 -> 40000
A7: 6 | B7: Shaikh Rasheed Pasha | C7: Finone Location Charges | D7: 45751 | E7: 25000 | F7: 0 | G7: 25000
A8: 7 | B8: Jhansi Art Director | C8: Finone Art fees and props | D8: 45752 | E8: 23500 | F8: 0 | G8: 23500
B9: Apoorv | D9: 45753 | E9: 40000 | G9: =E9+F9 -> 40000
A10: 8 | B10: A Mohan Kumar | C10: Catering Aadvance - Bambinos | D10: 45754 | E10: 10000 | F10: 0 | G10: 10000
A11: 9 | B11: Jhansi Art Director | C11: Bambinos Art 1st Installment | D11: 45754 | E11: 30000 | F11: 0 | G11: 30000
A12: 10 | B12: Bangaru Naidu | C12: Catering - Finone | D12: 45754 | E12: 12000 | F12: 0 | G12: 12000
A13: 11 | B13: Divyanshu | C13: Team Expenses | D13: 45754 | E13: 3629 | F13: 0 | G13: 3629
A14: 12 | B14: RPS Hospitality | C14: Bambinos Shoot Location Advance | D14: 45754 | E14: 10000 | F14: 0 | G14: 10000
A15: 13 | B15: RPS Hospitality | C15: Bambinos - 50k given(44680 got returned after deductions) | D15: 45754 | E15: 5320 | F15: 0 | G15: 5320
A16: 14 | B16: Angad Bhatia | C16: Bmabinos DOP Advance | D16: 45754 | E16: 20000 | F16: 0 | G16: 20000
A17: 15 | B17: MMT | D17: 45754 | E17: 18458 | G17: 18458
A18: 16 | B18: Eleven Labs | C18: Operational | D18: 45755 | E18: 447 | F18: 0 | G18: 447
A19: 17 | B19: RPS Hospitality | C19: Bambinos Shoot Location Balance | D19: 45755 | E19: 36400 | F19: 0 | G19: 36400 | H19: GST Input
A20: 18 | B20: Jhansi Art Director | C20: Bambinos Art 2nd Installment | D20: 45755 | E20: 20000 | F20: 0 | G20: 20000
A21: 19 | B21: Manikanta | C21: Equipment Payment from multiple shoots | D21: 45755 | E21: 20000 | F21: 0 | G21: 20000
A22: 20 | B22: A Mohan Kumar | C22: Catering Balance - bambinos | D22: 45756 | E22: 30000 | F22: 0 | G22: 30000
A23: 21 | B23: Rohit Dubey | C23: Sattva Voice Over Artist - 1st installment | D23: 45756 | E23: 15000 | F23: 0 | G23: 15000
A24: 22 | B24: Siva Gangadhar | C24: Makeup - Plastic Shoot | D24: 45756 | E24: 4500 | F24: 0 | G24: 4500
A25: 23 | B25: Akanksha | C25: Flight Booking Reimbursement | D25: 45756 | E25: 27213 | F25: 0 | G25: 27213
A26: 24 | B26: Eshvar Aditya | C26: Zentech DOP Fees | D26: 45756 | E26: 20000 | F26: 0 | G26: 20000
A27: 25 | B27: Dhanya | C27: Emcee for broadway and abhibus actor | D27: 45756 | E27: 28000 | F27: 0 | G27: 28000
A28: 26 | B28: RPS Hospitality | C28: Location Rent for Dabbahwala Shoot | D28: 45757 | E28: 35400 | F28: 0 | G28: 35400 | H28: GST Input
A29: 27 | B29: RPS Hospitality | C29: TDS payment | D29: 45757 | E29: 800 | F29: 0 | G29: 800
A30: 28 | B30: Rohit Dubey | C30: Sattva Voice Over Artist - 2nd installment | D30: 45757 | E30: 10000 | F30: 0 | G30: 10000
A31: 29 | B31: Angad Bahtia | C31: Bambinos DOP Balance | D31: 45757 | E31: 20000 | F31: 0 | G31: 20000
A32: 30 | B32: Syed Muneeb | C32: Zentech + Inhouse + Ip Shoot Actor fees | D32: 45757 | E32: 20000 | F32: 0 | G32: 20000
A33: 31 | B33: Yourdost | C33: March Invoice - Operational | D33: 45758 | E33: 17700 | F33: 0 | G33: 17700 | H33: GST Input
A34: 32 | B34: Yourdost | C34: Travel Reimbursement | D34: 45758 | E34: 11631 | F34: 0 | G34: 11631
A35: 33 | B35: Yourdost | C35: Travel Reimbursement | D35: 45758 | E35: 7109 | F35: 0 | G35: 7109
A36: 34 | B36: Mote Sai Sohan | C36: Hala Actor Fees | D36: 45758 | E36: 5430 | F36: 0 | G36: 5430
A37: 35 | B37: A Mohan Kumar | C37: Dabbahwala Catering | D37: 45758 | E37: 27500 | F37: 0 | G37: 27500
A38: 36 | B38: Shashank | C38: Broadway Event Videographer Fees | D38: 45758 | E38: 4000 | G38: 4000
A39: 37 | B39: Sound Space | C39: Podcast Sound Setup | D39: 45758 | E39: 2000 | F39: 0 | G39: 2000
A40: 38 | B40: Saksham | C40: Shoot Reimbursement | D40: 45758 | E40: 55270 | F40: 0 | G40: 55270
A41: 39 | B41: Open ai Subscription | C41: Operational | D41: 45759 | E41: 1796 | F41: 0 | G41: 1796
A42: 40 | B42: Jhansi Art Director | C42: Dabbahwala Full Payment | D42: 45760 | E42: 23000 | F42: 0 | G42: 23000
A43: 41 | B43: Resonate Studios | C43: Abhibus Sound Design | D43: 45761 | E43: 10000 | F43: 0 | G43: 10000
A44: 42 | B44: Manikanta | C44: Equipment Payment from multiple shoots | D44: 45761 | E44: 50000 | F44: 0 | G44: 50000
A45: 43 | B45: Esvaraditya | C45: Finone DOP | D45: 45761 | E45: 15000 | F45: 0 | G45: 15000
A46: 44 | B46: Vamshi | C46: Dabbahwala DOP payment | D46: 45761 | E46: 30000 | F46: 0 | G46: 30000
A47: 45 | B47: Satvik | C47: Team Expenses | D47: 45761 | E47: 2070 | F47: 0 | G47: 2070
A48: 46 | B48: Openai | C48: Operational | D48: 45761 | E48: 8085 | F48: 0 | G48: 8085
A49: 47 | B49: Symbont | C49: Sonic Lamb Location | D49: 45762 | E49: 41300 | F49: 0 | G49: 41300 | H49: GST INPUT
A50: 48 | B50: Manikanta | C50: Equipment Payment from multiple shoots | D50: 45762 | E50: 20000 | F50: 0 | G50: 20000
A51: 49 | B51: Jhansi Art Director | C51: Bambinos Art Fees | D51: 45762 | E51: 20000 | F51: 0 | G51: 20000
A52: 50 | B52: Shivani k Kapoor | C52: Bambinos Actor Travel & Food Bills | D52: 45762 | E52: 6605 | F52: 0 | G52: 6605
A53: 51 | B53: Jhansi Art Director | C53: Sonic Lamb Art Advance | D53: 45762 | E53: 15000 | F53: 0 | G53: 15000
A54: 52 | B54: Envato | C54: Operational | D54: 45765 | E54: 2938 | F54: 0 | G54: 2938
A55: 53 | B55: Heygen | C55: Operational | D55: 45765 | E55: 2582 | F55: 0 | G55: 2582
A56: 54 | B56: Venkata Praveen | C56: DIT - Dabbahwala | D56: 45768 | E56: 5000 | F56: 0 | G56: 5000
A57: 55 | B57: K Simon Peter | C57: Makeup - Dabbah Wala & Bambinos | D57: 45768 | E57: 14000 | F57: 0 | G57: 14000
A58: 56 | B58: Abhishek Boodepalli | C58: Sonic Lamb Actor | D58: 45768 | E58: 29700 | F58: 3300 | G58: =F58+E58 -> 33000
A59: 57 | B59: Divyanshu | C59: Team Expenses | D59: 45768 | E59: 859 | F59: 0 | G59: 859
A60: 58 | B60: Adobe Subscription | C60: Operational | D60: 45769 | E60: 2052.94 | F60: 0 | G60: 2052.94
A61: 59 | B61: Adobe Subscription | C61: Operational | D61: 45771 | E61: 1642.15 | F61: 0 | G61: 1642.15
A62: 60 | B62: Clickup Subscription | C62: Operational | D62: 45772 | E62: 13343 | F62: 0 | G62: 13343
A63: 61 | B63: Ala Subramanyam | C63: Sonic Lamb Actor | D63: 45772 | E63: 11000 | F63: 0 | G63: 11000
A64: 62 | B64: Tejaswini Actor | C64: Dabbahwala Actor | D64: 45772 | E64: 9639 | F64: 0 | G64: 9639
A65: 63 | B65: Anandvolu Venkat | C65: Sirisha - Dabbahwala Actor | D65: 45772 | E65: 7972 | F65: 0 | G65: 7972
A66: 64 | B66: Sandeep Sahu | C66: Finone Actor | D66: 45772 | E66: 15910 | F66: 0 | G66: 15910
A67: 65 | B67: Manikanta | C67: Equipment rental installment - Balance is still left | D67: 45772 | E67: 40000 | F67: 0 | G67: 40000
A68: 66 | B68: Divyanshu | C68: Team Expenses | D68: 45772 | E68: 1468 | F68: 0 | G68: 1468
A69: 67 | B69: Jhansi Art Director | C69: Sonic Lamb Art Fees and Balance Payment | D69: 45773 | E69: 53500 | F69: 0 | G69: 53500
A70: 68 | B70: MMT | D70: 45774 | E70: 40000 | G70: 40000
A71: 69 | B71: Prasanna | C71: Sonic Lamb Actress fees and Casting fees | D71: 45776 | E71: 16000 | G71: 16000
A72: 70 | B72: Bharath | C72: Sonic Lamb & Dabbahwala AD fees | D72: 45776 | E72: 17590 | G72: 17590
A73: 71 | B73: Junaid | C73: Nxtwave Cinematographer Advance and travel | D73: 45776 | E73: 12423 | G73: 12423
A74: 72 | B74: Om Travels | C74: Dabbahwala Travel - Production | D74: 45776 | E74: 6215 | G74: 6215
A75: 73 | B75: Akhil | C75: Extra TDS Deducted in salary - Refunded | D75: 45776 | E75: 25430 | G75: 25430
A76: 74 | B76: Viren Goswamy | C76: ASBL Pre Pitch Fees for Ai tools and Generation | D76: 45778 | E76: 10000 | G76: 10000
A77: 75 | B77: MMT | D77: 45779 | E77: 30000 | G77: 30000
A78: 76 | B78: Junaid | C78: Nxtwave Balance | D78: 45782 | E78: 10000 | G78: 10000
A79: 77 | B79: Jasraj Manga | C79: Dabbahwala Actor Fees | D79: 45782 | E79: 15833 | G79: 15833
A80: 78 | B80: Divyanshu | C80: team Shoot Expenses | D80: 45814 | E80: 9644 | G80: 9644
A81: 79 | B81: MMT - Apoorv & Satya | C81: Apoorv & Satya Hyd to Banglore Flight | D81: 45783 | E81: 9041 | G81: 9041
A82: 80 | B82: Utkarsha | C82: Bambinos Chief AD fees | D82: 45784 | E82: 15000 | G82: 15000
A83: 81 | B83: Eleven Labs | C83: Monthly Subscription | D83: 45785 | E83: 441 | G83: 441
A84: 82 | B84: MMT - Apoorv & Satya | C84: Apoorv & Satya Banglore to hyd return Flight | D84: 45786 | E84: 11028 | G84: 11028
A85: 83 | B85: Openai chat | C85: Operational | D85: 45789 | E85: 1781 | G85: 1781
A86: 84 | B86: Clickupaddon | C86: Operational | D86: 45791 | E86: 89 | G86: 89
A87: 85 | B87: Anmol Bhandari | C87: Aashirvaad Aata Shoot art director 50% fees | D87: 45792 | E87: 30000 | G87: 30000
A88: 86 | B88: Karan Uppal | C88: zomato packathon event Cine team advance | D88: 45792 | E88: 53000 | G88: 53000
A89: 87 | B89: Casting wire LLP | C89: Bambinos casting 50% advance | D89: 45792 | E89: 34800 | G89: 34800
... A109: 107 | B109: Sound Space | C109: Sound Equipments multiple shoots partial Payment | D109: 45798 | E109: 20000 | G109: 20000
A110: 108 | B110: Manikanta | C110: Equipment partial payment | D110: 45798 | E110: 29700 | F110: 300 | G110: 30000
A111: 109 | B111: Lingual | C111: Multiple VO payments | D111: 45798 | E111: 19440 | G111: 19440
A112: 110 | B112: Srestha | C112: Team expenses | D112: 45798 | E112: 1999 | G112: 1999
A113: 111 | B113: Adobe Subscription | C113: operational | D113: 45798 | E113: 2052 | G113: 2052
A114: 112 | B114: Clickup Subscription | C114: operational | D114: 45802 | E114: 15099 | G114: 15099
A115: 113 | B115: Saksham | C115: May Shoot & Operational Expenses | D115: 45802 | E115: 51803 | G115: 51803
A116: 114 | B116: Bharath | C116: Dabbahwala Fees - AD | D116: 45802 | E116: 8703 | G116: 8703
A117: 115 | B117: Mahesh Jala | C117: Nxtwave Art boy fees | D117: 45802 | E117: 1650 | G117: 1650
A118: 116 | B118: Karan Uppal | C118: Zomato Packathon Delhi team Balance Payments | D118: 45802 | E118: 51940 | G118: 51940
A119: 117 | B119: Sawan | C119: Team expenses | D119: 45802 | E119: 2557 | G119: 2557
...

Sheet Income Statement
D4: Income Statement (FY 2024-25)
D5: Particulars | E5: Atom | F5: Total
D6: Revenue | E6: =Revenue!F259 -> 65369420 | F6: =E6 -> 65369420
D7: Less:
D8: Shoot & Other Expenses | E8: =Expenses!E1297+Salaries!$K$27+Salaries!K61+Salaries!K91+Salaries!$K$123+Salaries!K159+Salaries!K191+Salaries!$K$231 -> #REF! | F8: =E8 -> #REF!
D9: Salaries
D10: April | E10: =Salaries!$J$27-Salaries!J7 -> #REF! | F10: =E10 -> #REF!
D11: May | E11: =Salaries!J61-Salaries!J37 -> #REF! | F11: =E11 -> #REF!
D12: June | E12: =Salaries!J91-Salaries!J69 -> #REF! | F12: =E12 -> #REF!
D13: July | E13: =Salaries!$J$123-Salaries!J97 -> #REF! | F13: =E13 -> #REF!
D14: August | E14: =Salaries!J159-Salaries!J134 -> #REF! | F14: =E14 -> #REF!
D15: September | E15: =Salaries!J191-Salaries!J165 -> #REF! | F15: =E15 -> #REF!
D16: October | E16: =Salaries!$J$231-Salaries!J198 -> #REF! | F16: =E16 -> #REF!
D17: November
D18: December
D19: January
D20: February
D21: March
D22: GST
D23: April GST
D24: May GST
D25: June GST
D26: July GST
D27: August GST
D28: September GST
... D34: March GST
D35: Total expenses | F35: =SUM(F8:F34) -> #REF!
D36: Profit | F36: =F6-F35 -> #REF!

Sheet Investment

Sheet monthly PL
C5: June Income Statement
C6: Particulars | D6: Amount | E6: Amount | F6: Accrual
C7: Gross Revenue | D7: 81,42,289 | E7: ='Income Statement'!F6 -> 65369420 | F7: =#REF! -> #REF!
C8: Less: GST | D8: 10,81,989 | E8: =E7*18/118 -> 9971606.4 | F8: =F7*18/118 -> #REF!
C9: Net Revenue | D9: 70,60,300 | E9: =E7-E8 -> 55397814 | F9: =F7-F8 -> #REF!
C10: Less: Expenses
C11: Shoot Expenses | D11: 43,57,611 | E11: ='Huemn Expenses'!G201-'Huemn Expenses'!L5-'Huemn Expenses'!L6-'Huemn Expenses'!L7-'Huemn Expenses'!L8-'Huemn Expenses'!L9-'Huemn Expenses'!L10+Salaries!K85 -> #REF! | F11: =E11+800000 -> #REF!
C12: Salaries | D12: 19,67,630 | E12: =#REF!+#REF!+#REF! -> #REF! | F12: =E12+700000 -> #REF!
C13: Total Expenses | D13: 63,25,241 | E13: =sum(E11:E12) -> #REF! | F13: =SUM(F11:F12) -> #REF!
C14: Profit | D14: 7,35,059 | E14: =E9-E13 -> #REF! | F14: =F9-F13 -> #REF! | G14: =F14/F7 -> #REF!
E15: =E14/E9 -> #REF!
H17: Cash Basis | K17: Accrual Basis
C18: Income Statement | H18: FY 23-24 Income Statement | K18: FY 23-24 Income Statement
C19: Particulars | D19: Last year | E19: Amount | H19: Particulars | I19: Last year | K19: Particulars | L19: Last year
C20: Gross Revenue | D20: =16876290 -> 16876290 | E20: =D20+E7 -> 82245710 | H20: Gross Revenue | I20: 1,68,76,20 | K20: Gross Revenue | L20: 1,82,22,830
C21: Less: GST | D21: =2350112 -> 2350112 | E21: =D21+E8 -> 12321718 | H21: Less: GST | I21: 23,50,112 | K21: Less: GST | L21: 27,79,754
C22: Net Revenue | D22: =D20-D21 -> 14526178 | E22: =E20-E21 -> 69923992 | H22: Net Revenue | I22: 1,45,26,178 | K22: Net Revenue | L22: 1,54,43,076
C23: Less: Expenses | H23: Less: Expenses | K23: Less: Expenses
C24: Shoot Expenses | D24: =6304815 -> 6304815 | E24: =D24+E11 -> #REF! | H24: Shoot Expenses | I24: 63,04,815 | K24: Shoot Expenses | L24: 66,30,065
C25: Salaries | D25: =5253618 -> 5253618 | E25: =D25+E12 -> #REF! | H25: Salaries | I25: 52,53,618 | K25: Salaries | L25: 52,66,676
C26: Total Expenses | D26: =D24+D25 -> 11558433 | E26: =sum(E24:E25) -> #REF! | H26: Total Expenses | I26: 1,15,58,433 | K26: Total Expenses | L26: 1,18,96,741
C27: Profit | D27: =D22-D26 -> 2967745 | E27: =E22-E26 -> #REF! | F27: =D27/D20 -> 0.17585293 | H27: Profit | I27: 29,67,745 | K27: Profit | L27: 35,46,335
C28: Share of each partner | D28: =D27/2 -> 1483872.5 | E28: =E27/2 -> #REF! | H28: Profit % | I28: 0.176 | K28: Profit % | L28: 0.195
C31: April to 20th August Income Statement | H31: FY 24-25 Income Statement | K31: FY 24-25 Income Statement
C32: Particulars | D32: Amount | E32: Amount | H32: Particulars | I32: Last year | K32: Particulars | L32: Last year
C33: Revenue | E33: =Revenue!F138+Revenue!G138 -> #REF! | H33: Gross Revenue | I33: 81,42,289 | K33: Gross Revenue | L33: 1,29,20,919
C34: Less | H34: Less: GST | I34: 12,42,044 | K34: Less: GST | L34: 19,70,988
C35: GST | D35: =E33*18/118 -> #REF! | H35: Net Revenue | I35: 69,00,245 | K35: Net Revenue | L35: 1,09,49,931
C36: Shoot Expenses | D36: =#REF! -> #REF! | H36: Less: Expenses | K36: Less: Expenses
C37: Salaries | D37: =#REF!+#REF!+#REF!+#REF! -> #REF! | H37: Shoot Expenses | I37: 43,57,611 | K37: Shoot Expenses | L37: 43,57,611
C38: Total Expenses | E38: =sum(D35:D37) -> #REF! | H38: Salaries | I38: 19,67,630 | K38: Salaries | L38: 19,67,630
C39: loss | E39: =E33-E38 -> #REF! | H39: Total Expenses | I39: 63,25,241 | K39: Total Expenses | L39: 63,25,241
H40: Profit | I40: 5,75,004 | K40: Profit | L40: 46,24,690
H41: Profit % | I41: 0.0833 | K41: Profit % | L41: 0.42

Sheet Quarterly Revenue
C8: April | D8: Amount | E8: May | F8: Amount 2 | G8: June | H8: Amount 3
C9: Think9(Broadway) | D9: 59000 | E9: Sattva IP's | F9: 3540000 | G9: Jumpp - Finfutech | H9: 3050300
C10: Pranita Bajoria | D10: 15000 | E10: Select(Celeket Gadgets) | F10: 1700000 | G10: Jumpp Social Retainer - Finvasia | H10: 619500
C11: Nxtwave(3 vdos) | D11: 283200 | E11: TCS(Ayanz food lab) | F11: 2458500 | G11: Zomato ITR Social | H11: 324500
C12: ITC Sunrise(Social) | D12: 177000 | E12: Dabur | F12: 572300 | G12: Medanta Hospitals | H12: =800000+144000 -> 944000
C13: Zomato Packathon Event | D13: 684400 | G13: Zomato Reactivate | H13: 767000
C14: Zomato Voice Over - dubs | D14: 100300 | G14: Hala Mobility - June(Extra) | H14: 118000
C15: Nxtwave Lab Innovation Vdo | D15: 330400 | G15: Karya & Gravityzip | H15: 3044400
G16: Sonic lamb | H16: 590000
G17: Nxtwave green Screen Shoot | H17: 29500
D18: =SUM(D9:D17) -> 1649300 | F18: =SUM(F9:F17) -> 8270800 | H18: =SUM(H9:H17) -> 9487200
E25: 405 | F25: TDS | H25: 45910 | I25: 427517 | M25: done
E26: 406 | F26: TDS | H26: 45910 | I26: 103440 | M26: done
E27: 407 | F27: TDS | H27: 45910 | I27: 22163 | M27: done
E28: 408 | F28: TDS | H28: 45911 | I28: 9000 | M28: done
G30: June
G31: Jumpp - Finfutech | H31: 3050300
G32: Jumpp Social Retainer - Finvasia | H32: 619500
G33: Zomato ITR Social | H33: 324500
G34: Medanta Hospitals | H34: =800000+144000 -> 944000
G35: Zomato Reactivate | H35: 767000
G36: Hala Mobility - June(Extra) | H36: 118000
G37: Karya & Gravityzip | H37: 3044400
G38: Nxtwave green Screen Shoot | H38: 29500
